{
  "projectName": "MyEvaluations.Business.Common",
  "parsedAt": "2026-02-20T14:23:22.818Z",
  "parserUsed": "tree-sitter",
  "classCount": 103,
  "classes": [
    {
      "name": "BusinessObject",
      "namespace": "MyEvaluations.Business.Common",
      "baseClass": null,
      "interfaces": [],
      "isAbstract": true,
      "isStatic": false,
      "methods": [],
      "properties": [],
      "storedProcedureCalls": [],
      "filePath": "MyEvaluations.Business.Common/BusinessObject.cs"
    },
    {
      "name": "CacheManager",
      "namespace": "MyEvaluations.Business.Common",
      "baseClass": "Manager",
      "interfaces": [],
      "isAbstract": false,
      "isStatic": false,
      "methods": [],
      "properties": [],
      "storedProcedureCalls": [],
      "filePath": "MyEvaluations.Business.Common/CacheManager.cs"
    },
    {
      "name": "CalculateDateDifference",
      "namespace": "MyEvaluations.Business.Common",
      "baseClass": null,
      "interfaces": [],
      "isAbstract": false,
      "isStatic": false,
      "methods": [],
      "properties": [],
      "storedProcedureCalls": [],
      "filePath": "MyEvaluations.Business.Common/CalculateTimeDiff.cs"
    },
    {
      "name": "EventData",
      "namespace": "MyEvaluations.Business.Common",
      "baseClass": null,
      "interfaces": [],
      "isAbstract": false,
      "isStatic": false,
      "methods": [],
      "properties": [],
      "storedProcedureCalls": [],
      "filePath": "MyEvaluations.Business.Common/CommonTypes.cs"
    },
    {
      "name": "EventInfo",
      "namespace": "MyEvaluations.Business.Common",
      "baseClass": null,
      "interfaces": [],
      "isAbstract": false,
      "isStatic": false,
      "methods": [],
      "properties": [],
      "storedProcedureCalls": [],
      "filePath": "MyEvaluations.Business.Common/CommonTypes.cs"
    },
    {
      "name": "BusinessEventArgs",
      "namespace": "MyEvaluations.Business.Common",
      "baseClass": "EventArgs",
      "interfaces": [],
      "isAbstract": false,
      "isStatic": false,
      "methods": [],
      "properties": [],
      "storedProcedureCalls": [],
      "filePath": "MyEvaluations.Business.Common/CommonTypes.cs"
    },
    {
      "name": "Constants",
      "namespace": "MyEvaluations.Business.Common",
      "baseClass": null,
      "interfaces": [],
      "isAbstract": false,
      "isStatic": false,
      "methods": [],
      "properties": [],
      "storedProcedureCalls": [],
      "filePath": "MyEvaluations.Business.Common/Constants.cs"
    },
    {
      "name": "DashBoard",
      "namespace": "MyEvaluations.Business.Common",
      "baseClass": null,
      "interfaces": [],
      "isAbstract": false,
      "isStatic": false,
      "methods": [],
      "properties": [],
      "storedProcedureCalls": [],
      "filePath": "MyEvaluations.Business.Common/DashBoard.cs"
    },
    {
      "name": "ToDos",
      "namespace": "MyEvaluations.Business.Common",
      "baseClass": null,
      "interfaces": [],
      "isAbstract": false,
      "isStatic": false,
      "methods": [],
      "properties": [],
      "storedProcedureCalls": [],
      "filePath": "MyEvaluations.Business.Common/DashBoard.cs"
    },
    {
      "name": "ModulesSystemImplementation",
      "namespace": "MyEvaluations.Business.Common",
      "baseClass": null,
      "interfaces": [],
      "isAbstract": false,
      "isStatic": false,
      "methods": [],
      "properties": [],
      "storedProcedureCalls": [],
      "filePath": "MyEvaluations.Business.Common/DashBoard.cs"
    },
    {
      "name": "DashboardSystemImplementation",
      "namespace": "MyEvaluations.Business.Common",
      "baseClass": null,
      "interfaces": [],
      "isAbstract": false,
      "isStatic": false,
      "methods": [],
      "properties": [],
      "storedProcedureCalls": [],
      "filePath": "MyEvaluations.Business.Common/DashBoard.cs"
    },
    {
      "name": "Progress",
      "namespace": "MyEvaluations.Business.Common",
      "baseClass": null,
      "interfaces": [],
      "isAbstract": false,
      "isStatic": false,
      "methods": [],
      "properties": [],
      "storedProcedureCalls": [],
      "filePath": "MyEvaluations.Business.Common/DashBoard.cs"
    },
    {
      "name": "SubModulesSystemImplementation",
      "namespace": "MyEvaluations.Business.Common",
      "baseClass": null,
      "interfaces": [],
      "isAbstract": false,
      "isStatic": false,
      "methods": [],
      "properties": [],
      "storedProcedureCalls": [],
      "filePath": "MyEvaluations.Business.Common/DashBoard.cs"
    },
    {
      "name": "EvaluationFormModulesSystemImplementation",
      "namespace": "MyEvaluations.Business.Common",
      "baseClass": null,
      "interfaces": [],
      "isAbstract": false,
      "isStatic": false,
      "methods": [],
      "properties": [],
      "storedProcedureCalls": [],
      "filePath": "MyEvaluations.Business.Common/DashBoard.cs"
    },
    {
      "name": "SubSubModules",
      "namespace": "MyEvaluations.Business.Common",
      "baseClass": null,
      "interfaces": [],
      "isAbstract": false,
      "isStatic": false,
      "methods": [],
      "properties": [],
      "storedProcedureCalls": [],
      "filePath": "MyEvaluations.Business.Common/DashBoard.cs"
    },
    {
      "name": "Item",
      "namespace": "MyEvaluations.Business.Common",
      "baseClass": null,
      "interfaces": [],
      "isAbstract": false,
      "isStatic": false,
      "methods": [],
      "properties": [],
      "storedProcedureCalls": [],
      "filePath": "MyEvaluations.Business.Common/DashBoard.cs"
    },
    {
      "name": "Status",
      "namespace": "MyEvaluations.Business.Common",
      "baseClass": null,
      "interfaces": [],
      "isAbstract": false,
      "isStatic": false,
      "methods": [],
      "properties": [],
      "storedProcedureCalls": [],
      "filePath": "MyEvaluations.Business.Common/DashBoard.cs"
    },
    {
      "name": "DashBoardSystemImplementation",
      "namespace": "MyEvaluations.Business.Common",
      "baseClass": null,
      "interfaces": [],
      "isAbstract": false,
      "isStatic": false,
      "methods": [],
      "properties": [],
      "storedProcedureCalls": [],
      "filePath": "MyEvaluations.Business.Common/DashBoard.cs"
    },
    {
      "name": "Dashboardtodo",
      "namespace": "MyEvaluations.Business.Common",
      "baseClass": null,
      "interfaces": [],
      "isAbstract": false,
      "isStatic": false,
      "methods": [],
      "properties": [],
      "storedProcedureCalls": [],
      "filePath": "MyEvaluations.Business.Common/DashBoard.cs"
    },
    {
      "name": "DashboardThingstodo",
      "namespace": "MyEvaluations.Business.Common",
      "baseClass": null,
      "interfaces": [],
      "isAbstract": false,
      "isStatic": false,
      "methods": [],
      "properties": [],
      "storedProcedureCalls": [],
      "filePath": "MyEvaluations.Business.Common/DashBoard.cs"
    },
    {
      "name": "DashboardMessages",
      "namespace": "MyEvaluations.Business.Common",
      "baseClass": null,
      "interfaces": [],
      "isAbstract": false,
      "isStatic": false,
      "methods": [],
      "properties": [],
      "storedProcedureCalls": [],
      "filePath": "MyEvaluations.Business.Common/DashBoard.cs"
    },
    {
      "name": "MessageItems",
      "namespace": "MyEvaluations.Business.Common",
      "baseClass": null,
      "interfaces": [],
      "isAbstract": false,
      "isStatic": false,
      "methods": [],
      "properties": [],
      "storedProcedureCalls": [],
      "filePath": "MyEvaluations.Business.Common/DashBoard.cs"
    },
    {
      "name": "DashBoardShortcuts",
      "namespace": "MyEvaluations.Business.Common",
      "baseClass": null,
      "interfaces": [],
      "isAbstract": false,
      "isStatic": false,
      "methods": [],
      "properties": [],
      "storedProcedureCalls": [],
      "filePath": "MyEvaluations.Business.Common/DashBoard.cs"
    },
    {
      "name": "DashBoardSubmitShortcuts",
      "namespace": "MyEvaluations.Business.Common",
      "baseClass": null,
      "interfaces": [],
      "isAbstract": false,
      "isStatic": false,
      "methods": [],
      "properties": [],
      "storedProcedureCalls": [],
      "filePath": "MyEvaluations.Business.Common/DashBoard.cs"
    },
    {
      "name": "DashBoardSubShortcuts",
      "namespace": "MyEvaluations.Business.Common",
      "baseClass": null,
      "interfaces": [],
      "isAbstract": false,
      "isStatic": false,
      "methods": [],
      "properties": [],
      "storedProcedureCalls": [],
      "filePath": "MyEvaluations.Business.Common/DashBoard.cs"
    },
    {
      "name": "DashBoardSubShortcutitems",
      "namespace": "MyEvaluations.Business.Common",
      "baseClass": null,
      "interfaces": [],
      "isAbstract": false,
      "isStatic": false,
      "methods": [],
      "properties": [],
      "storedProcedureCalls": [],
      "filePath": "MyEvaluations.Business.Common/DashBoard.cs"
    },
    {
      "name": "ActionTrigger",
      "namespace": "MyEvaluations.Business.Common",
      "baseClass": null,
      "interfaces": [],
      "isAbstract": false,
      "isStatic": false,
      "methods": [],
      "properties": [],
      "storedProcedureCalls": [],
      "filePath": "MyEvaluations.Business.Common/DashBoard.cs"
    },
    {
      "name": "Schedule",
      "namespace": "MyEvaluations.Business.Common",
      "baseClass": null,
      "interfaces": [],
      "isAbstract": false,
      "isStatic": false,
      "methods": [],
      "properties": [],
      "storedProcedureCalls": [],
      "filePath": "MyEvaluations.Business.Common/DashBoard.cs"
    },
    {
      "name": "RotationData",
      "namespace": "MyEvaluations.Business.Common",
      "baseClass": null,
      "interfaces": [],
      "isAbstract": false,
      "isStatic": false,
      "methods": [],
      "properties": [],
      "storedProcedureCalls": [],
      "filePath": "MyEvaluations.Business.Common/DashBoard.cs"
    },
    {
      "name": "Assigned",
      "namespace": "MyEvaluations.Business.Common",
      "baseClass": null,
      "interfaces": [],
      "isAbstract": false,
      "isStatic": false,
      "methods": [],
      "properties": [],
      "storedProcedureCalls": [],
      "filePath": "MyEvaluations.Business.Common/DashBoard.cs"
    },
    {
      "name": "EventDetails",
      "namespace": "MyEvaluations.Business.Common",
      "baseClass": null,
      "interfaces": [],
      "isAbstract": false,
      "isStatic": false,
      "methods": [],
      "properties": [],
      "storedProcedureCalls": [],
      "filePath": "MyEvaluations.Business.Common/DashBoard.cs"
    },
    {
      "name": "ScheduleEventId",
      "namespace": "MyEvaluations.Business.Common",
      "baseClass": null,
      "interfaces": [],
      "isAbstract": false,
      "isStatic": false,
      "methods": [],
      "properties": [],
      "storedProcedureCalls": [],
      "filePath": "MyEvaluations.Business.Common/DashBoard.cs"
    },
    {
      "name": "Event",
      "namespace": "MyEvaluations.Business.Common",
      "baseClass": null,
      "interfaces": [],
      "isAbstract": false,
      "isStatic": false,
      "methods": [],
      "properties": [],
      "storedProcedureCalls": [],
      "filePath": "MyEvaluations.Business.Common/DashBoard.cs"
    },
    {
      "name": "TopicData",
      "namespace": "MyEvaluations.Business.Common",
      "baseClass": null,
      "interfaces": [],
      "isAbstract": false,
      "isStatic": false,
      "methods": [],
      "properties": [],
      "storedProcedureCalls": [],
      "filePath": "MyEvaluations.Business.Common/DashBoard.cs"
    },
    {
      "name": "AttachmentData",
      "namespace": "MyEvaluations.Business.Common",
      "baseClass": null,
      "interfaces": [],
      "isAbstract": false,
      "isStatic": false,
      "methods": [],
      "properties": [],
      "storedProcedureCalls": [],
      "filePath": "MyEvaluations.Business.Common/DashBoard.cs"
    },
    {
      "name": "AverageScore",
      "namespace": "MyEvaluations.Business.Common",
      "baseClass": null,
      "interfaces": [],
      "isAbstract": false,
      "isStatic": false,
      "methods": [],
      "properties": [],
      "storedProcedureCalls": [],
      "filePath": "MyEvaluations.Business.Common/DashBoard.cs"
    },
    {
      "name": "AverageScoreHistogram",
      "namespace": "MyEvaluations.Business.Common",
      "baseClass": null,
      "interfaces": [],
      "isAbstract": false,
      "isStatic": false,
      "methods": [],
      "properties": [],
      "storedProcedureCalls": [],
      "filePath": "MyEvaluations.Business.Common/DashBoard.cs"
    },
    {
      "name": "AverageScoreOverTime",
      "namespace": "MyEvaluations.Business.Common",
      "baseClass": null,
      "interfaces": [],
      "isAbstract": false,
      "isStatic": false,
      "methods": [],
      "properties": [],
      "storedProcedureCalls": [],
      "filePath": "MyEvaluations.Business.Common/DashBoard.cs"
    },
    {
      "name": "Quiz",
      "namespace": "MyEvaluations.Business.Common",
      "baseClass": null,
      "interfaces": [],
      "isAbstract": false,
      "isStatic": false,
      "methods": [],
      "properties": [],
      "storedProcedureCalls": [],
      "filePath": "MyEvaluations.Business.Common/DashBoard.cs"
    },
    {
      "name": "QuizPerformanceResponseModel",
      "namespace": "MyEvaluations.Business.Common",
      "baseClass": null,
      "interfaces": [],
      "isAbstract": false,
      "isStatic": false,
      "methods": [],
      "properties": [],
      "storedProcedureCalls": [],
      "filePath": "MyEvaluations.Business.Common/DashBoard.cs"
    },
    {
      "name": "Expired",
      "namespace": "MyEvaluations.Business.Common",
      "baseClass": null,
      "interfaces": [],
      "isAbstract": false,
      "isStatic": false,
      "methods": [],
      "properties": [],
      "storedProcedureCalls": [],
      "filePath": "MyEvaluations.Business.Common/DashBoard.cs"
    },
    {
      "name": "ClinicalHourResponseModel",
      "namespace": "MyEvaluations.Business.Common",
      "baseClass": null,
      "interfaces": [],
      "isAbstract": false,
      "isStatic": false,
      "methods": [],
      "properties": [],
      "storedProcedureCalls": [],
      "filePath": "MyEvaluations.Business.Common/DashBoard.cs"
    },
    {
      "name": "ReviewalRate",
      "namespace": "MyEvaluations.Business.Common",
      "baseClass": null,
      "interfaces": [],
      "isAbstract": false,
      "isStatic": false,
      "methods": [],
      "properties": [],
      "storedProcedureCalls": [],
      "filePath": "MyEvaluations.Business.Common/DashBoard.cs"
    },
    {
      "name": "SubmittedCurrently",
      "namespace": "MyEvaluations.Business.Common",
      "baseClass": null,
      "interfaces": [],
      "isAbstract": false,
      "isStatic": false,
      "methods": [],
      "properties": [],
      "storedProcedureCalls": [],
      "filePath": "MyEvaluations.Business.Common/DashBoard.cs"
    },
    {
      "name": "ScheduledCurrently",
      "namespace": "MyEvaluations.Business.Common",
      "baseClass": null,
      "interfaces": [],
      "isAbstract": false,
      "isStatic": false,
      "methods": [],
      "properties": [],
      "storedProcedureCalls": [],
      "filePath": "MyEvaluations.Business.Common/DashBoard.cs"
    },
    {
      "name": "ViolationRateOverTime",
      "namespace": "MyEvaluations.Business.Common",
      "baseClass": null,
      "interfaces": [],
      "isAbstract": false,
      "isStatic": false,
      "methods": [],
      "properties": [],
      "storedProcedureCalls": [],
      "filePath": "MyEvaluations.Business.Common/DashBoard.cs"
    },
    {
      "name": "PerformanceTaskCompletionModel",
      "namespace": "MyEvaluations.Business.Common",
      "baseClass": null,
      "interfaces": [],
      "isAbstract": false,
      "isStatic": false,
      "methods": [],
      "properties": [],
      "storedProcedureCalls": [],
      "filePath": "MyEvaluations.Business.Common/DashBoard.cs"
    },
    {
      "name": "PerformanceTaskCompletionRate",
      "namespace": "MyEvaluations.Business.Common",
      "baseClass": null,
      "interfaces": [],
      "isAbstract": false,
      "isStatic": false,
      "methods": [],
      "properties": [],
      "storedProcedureCalls": [],
      "filePath": "MyEvaluations.Business.Common/DashBoard.cs"
    },
    {
      "name": "PerformanceTaskCompletionRateOvertTime",
      "namespace": "MyEvaluations.Business.Common",
      "baseClass": null,
      "interfaces": [],
      "isAbstract": false,
      "isStatic": false,
      "methods": [],
      "properties": [],
      "storedProcedureCalls": [],
      "filePath": "MyEvaluations.Business.Common/DashBoard.cs"
    },
    {
      "name": "PerformancecompletionRateByType",
      "namespace": "MyEvaluations.Business.Common",
      "baseClass": null,
      "interfaces": [],
      "isAbstract": false,
      "isStatic": false,
      "methods": [],
      "properties": [],
      "storedProcedureCalls": [],
      "filePath": "MyEvaluations.Business.Common/DashBoard.cs"
    },
    {
      "name": "PublicationsResearchResponseModel",
      "namespace": "MyEvaluations.Business.Common",
      "baseClass": null,
      "interfaces": [],
      "isAbstract": false,
      "isStatic": false,
      "methods": [],
      "properties": [],
      "storedProcedureCalls": [],
      "filePath": "MyEvaluations.Business.Common/DashBoard.cs"
    },
    {
      "name": "PerformanceEvalutionModel",
      "namespace": "MyEvaluations.Business.Common",
      "baseClass": null,
      "interfaces": [],
      "isAbstract": false,
      "isStatic": false,
      "methods": [],
      "properties": [],
      "storedProcedureCalls": [],
      "filePath": "MyEvaluations.Business.Common/DashBoard.cs"
    },
    {
      "name": "PerformanceEvalutaionaverageDaysToComplete",
      "namespace": "MyEvaluations.Business.Common",
      "baseClass": null,
      "interfaces": [],
      "isAbstract": false,
      "isStatic": false,
      "methods": [],
      "properties": [],
      "storedProcedureCalls": [],
      "filePath": "MyEvaluations.Business.Common/DashBoard.cs"
    },
    {
      "name": "PerformanceEvalutaionpendingCurrently",
      "namespace": "MyEvaluations.Business.Common",
      "baseClass": null,
      "interfaces": [],
      "isAbstract": false,
      "isStatic": false,
      "methods": [],
      "properties": [],
      "storedProcedureCalls": [],
      "filePath": "MyEvaluations.Business.Common/DashBoard.cs"
    },
    {
      "name": "PerformanceEvalutaionOverdueCurrently",
      "namespace": "MyEvaluations.Business.Common",
      "baseClass": null,
      "interfaces": [],
      "isAbstract": false,
      "isStatic": false,
      "methods": [],
      "properties": [],
      "storedProcedureCalls": [],
      "filePath": "MyEvaluations.Business.Common/DashBoard.cs"
    },
    {
      "name": "PerformanceEvalutaionaverageDaysToCompleteOverTime",
      "namespace": "MyEvaluations.Business.Common",
      "baseClass": null,
      "interfaces": [],
      "isAbstract": false,
      "isStatic": false,
      "methods": [],
      "properties": [],
      "storedProcedureCalls": [],
      "filePath": "MyEvaluations.Business.Common/DashBoard.cs"
    },
    {
      "name": "PerformanceEvalutaionaverageDaysToCompleteHistogram",
      "namespace": "MyEvaluations.Business.Common",
      "baseClass": null,
      "interfaces": [],
      "isAbstract": false,
      "isStatic": false,
      "methods": [],
      "properties": [],
      "storedProcedureCalls": [],
      "filePath": "MyEvaluations.Business.Common/DashBoard.cs"
    },
    {
      "name": "SubmissionRate",
      "namespace": "MyEvaluations.Business.Common",
      "baseClass": null,
      "interfaces": [],
      "isAbstract": false,
      "isStatic": false,
      "methods": [],
      "properties": [],
      "storedProcedureCalls": [],
      "filePath": "MyEvaluations.Business.Common/DashBoard.cs"
    },
    {
      "name": "SubmissionRateByType",
      "namespace": "MyEvaluations.Business.Common",
      "baseClass": null,
      "interfaces": [],
      "isAbstract": false,
      "isStatic": false,
      "methods": [],
      "properties": [],
      "storedProcedureCalls": [],
      "filePath": "MyEvaluations.Business.Common/DashBoard.cs"
    },
    {
      "name": "SubmissionsOverTime",
      "namespace": "MyEvaluations.Business.Common",
      "baseClass": null,
      "interfaces": [],
      "isAbstract": false,
      "isStatic": false,
      "methods": [],
      "properties": [],
      "storedProcedureCalls": [],
      "filePath": "MyEvaluations.Business.Common/DashBoard.cs"
    },
    {
      "name": "ImplementedInAllYears",
      "namespace": "MyEvaluations.Business.Common",
      "baseClass": null,
      "interfaces": [],
      "isAbstract": false,
      "isStatic": false,
      "methods": [],
      "properties": [],
      "storedProcedureCalls": [],
      "filePath": "MyEvaluations.Business.Common/DashBoard.cs"
    },
    {
      "name": "QualityImprovementResponseModel",
      "namespace": "MyEvaluations.Business.Common",
      "baseClass": null,
      "interfaces": [],
      "isAbstract": false,
      "isStatic": false,
      "methods": [],
      "properties": [],
      "storedProcedureCalls": [],
      "filePath": "MyEvaluations.Business.Common/DashBoard.cs"
    },
    {
      "name": "SubmittedInAllYears",
      "namespace": "MyEvaluations.Business.Common",
      "baseClass": null,
      "interfaces": [],
      "isAbstract": false,
      "isStatic": false,
      "methods": [],
      "properties": [],
      "storedProcedureCalls": [],
      "filePath": "MyEvaluations.Business.Common/DashBoard.cs"
    },
    {
      "name": "UnderReviewCurrently",
      "namespace": "MyEvaluations.Business.Common",
      "baseClass": null,
      "interfaces": [],
      "isAbstract": false,
      "isStatic": false,
      "methods": [],
      "properties": [],
      "storedProcedureCalls": [],
      "filePath": "MyEvaluations.Business.Common/DashBoard.cs"
    },
    {
      "name": "ProceduresData",
      "namespace": "MyEvaluations.Business.Common",
      "baseClass": null,
      "interfaces": [],
      "isAbstract": false,
      "isStatic": false,
      "methods": [],
      "properties": [],
      "storedProcedureCalls": [],
      "filePath": "MyEvaluations.Business.Common/DashBoard.cs"
    },
    {
      "name": "ProcedureObjectiveData",
      "namespace": "MyEvaluations.Business.Common",
      "baseClass": null,
      "interfaces": [],
      "isAbstract": false,
      "isStatic": false,
      "methods": [],
      "properties": [],
      "storedProcedureCalls": [],
      "filePath": "MyEvaluations.Business.Common/DashBoard.cs"
    },
    {
      "name": "AcceptanceRateData",
      "namespace": "MyEvaluations.Business.Common",
      "baseClass": null,
      "interfaces": [],
      "isAbstract": false,
      "isStatic": false,
      "methods": [],
      "properties": [],
      "storedProcedureCalls": [],
      "filePath": "MyEvaluations.Business.Common/DashBoard.cs"
    },
    {
      "name": "AcceptanceRateByProceduredata",
      "namespace": "MyEvaluations.Business.Common",
      "baseClass": null,
      "interfaces": [],
      "isAbstract": false,
      "isStatic": false,
      "methods": [],
      "properties": [],
      "storedProcedureCalls": [],
      "filePath": "MyEvaluations.Business.Common/DashBoard.cs"
    },
    {
      "name": "ProcedureacceptanceBreakdown",
      "namespace": "MyEvaluations.Business.Common",
      "baseClass": null,
      "interfaces": [],
      "isAbstract": false,
      "isStatic": false,
      "methods": [],
      "properties": [],
      "storedProcedureCalls": [],
      "filePath": "MyEvaluations.Business.Common/DashBoard.cs"
    },
    {
      "name": "Competencies",
      "namespace": "MyEvaluations.Business.Common",
      "baseClass": null,
      "interfaces": [],
      "isAbstract": false,
      "isStatic": false,
      "methods": [],
      "properties": [],
      "storedProcedureCalls": [],
      "filePath": "MyEvaluations.Business.Common/DashBoard.cs"
    },
    {
      "name": "Myinsighst",
      "namespace": "MyEvaluations.Business.Common",
      "baseClass": null,
      "interfaces": [],
      "isAbstract": false,
      "isStatic": false,
      "methods": [],
      "properties": [],
      "storedProcedureCalls": [],
      "filePath": "MyEvaluations.Business.Common/DashBoard.cs"
    },
    {
      "name": "CoreCompetencies",
      "namespace": "MyEvaluations.Business.Common",
      "baseClass": null,
      "interfaces": [],
      "isAbstract": false,
      "isStatic": false,
      "methods": [],
      "properties": [],
      "storedProcedureCalls": [],
      "filePath": "MyEvaluations.Business.Common/DashBoard.cs"
    },
    {
      "name": "OtherCompetencies",
      "namespace": "MyEvaluations.Business.Common",
      "baseClass": null,
      "interfaces": [],
      "isAbstract": false,
      "isStatic": false,
      "methods": [],
      "properties": [],
      "storedProcedureCalls": [],
      "filePath": "MyEvaluations.Business.Common/DashBoard.cs"
    },
    {
      "name": "Score",
      "namespace": "MyEvaluations.Business.Common",
      "baseClass": null,
      "interfaces": [],
      "isAbstract": false,
      "isStatic": false,
      "methods": [],
      "properties": [],
      "storedProcedureCalls": [],
      "filePath": "MyEvaluations.Business.Common/DashBoard.cs"
    },
    {
      "name": "ScoreOverTime",
      "namespace": "MyEvaluations.Business.Common",
      "baseClass": null,
      "interfaces": [],
      "isAbstract": false,
      "isStatic": false,
      "methods": [],
      "properties": [],
      "storedProcedureCalls": [],
      "filePath": "MyEvaluations.Business.Common/DashBoard.cs"
    },
    {
      "name": "PerformanceImprovementPlans",
      "namespace": "MyEvaluations.Business.Common",
      "baseClass": null,
      "interfaces": [],
      "isAbstract": false,
      "isStatic": false,
      "methods": [],
      "properties": [],
      "storedProcedureCalls": [],
      "filePath": "MyEvaluations.Business.Common/DashBoard.cs"
    },
    {
      "name": "CompetenciesbyId",
      "namespace": "MyEvaluations.Business.Common",
      "baseClass": null,
      "interfaces": [],
      "isAbstract": false,
      "isStatic": false,
      "methods": [],
      "properties": [],
      "storedProcedureCalls": [],
      "filePath": "MyEvaluations.Business.Common/DashBoard.cs"
    },
    {
      "name": "Subcompetencies",
      "namespace": "MyEvaluations.Business.Common",
      "baseClass": null,
      "interfaces": [],
      "isAbstract": false,
      "isStatic": false,
      "methods": [],
      "properties": [],
      "storedProcedureCalls": [],
      "filePath": "MyEvaluations.Business.Common/DashBoard.cs"
    },
    {
      "name": "SubcompetenciesData",
      "namespace": "MyEvaluations.Business.Common",
      "baseClass": null,
      "interfaces": [],
      "isAbstract": false,
      "isStatic": false,
      "methods": [],
      "properties": [],
      "storedProcedureCalls": [],
      "filePath": "MyEvaluations.Business.Common/DashBoard.cs"
    },
    {
      "name": "SubcompetencyScoreOvertime",
      "namespace": "MyEvaluations.Business.Common",
      "baseClass": null,
      "interfaces": [],
      "isAbstract": false,
      "isStatic": false,
      "methods": [],
      "properties": [],
      "storedProcedureCalls": [],
      "filePath": "MyEvaluations.Business.Common/DashBoard.cs"
    },
    {
      "name": "CompetencyScoreOvertime",
      "namespace": "MyEvaluations.Business.Common",
      "baseClass": null,
      "interfaces": [],
      "isAbstract": false,
      "isStatic": false,
      "methods": [],
      "properties": [],
      "storedProcedureCalls": [],
      "filePath": "MyEvaluations.Business.Common/DashBoard.cs"
    },
    {
      "name": "EPADashboard",
      "namespace": "MyEvaluations.Business.Common",
      "baseClass": null,
      "interfaces": [],
      "isAbstract": false,
      "isStatic": false,
      "methods": [],
      "properties": [],
      "storedProcedureCalls": [],
      "filePath": "MyEvaluations.Business.Common/DashBoard.cs"
    },
    {
      "name": "EPAGroup",
      "namespace": "MyEvaluations.Business.Common",
      "baseClass": null,
      "interfaces": [],
      "isAbstract": false,
      "isStatic": false,
      "methods": [],
      "properties": [],
      "storedProcedureCalls": [],
      "filePath": "MyEvaluations.Business.Common/DashBoard.cs"
    },
    {
      "name": "EPAScore",
      "namespace": "MyEvaluations.Business.Common",
      "baseClass": null,
      "interfaces": [],
      "isAbstract": false,
      "isStatic": false,
      "methods": [],
      "properties": [],
      "storedProcedureCalls": [],
      "filePath": "MyEvaluations.Business.Common/DashBoard.cs"
    },
    {
      "name": "EPAS",
      "namespace": "MyEvaluations.Business.Common",
      "baseClass": null,
      "interfaces": [],
      "isAbstract": false,
      "isStatic": false,
      "methods": [],
      "properties": [],
      "storedProcedureCalls": [],
      "filePath": "MyEvaluations.Business.Common/DashBoard.cs"
    },
    {
      "name": "EPAScoreOverTime",
      "namespace": "MyEvaluations.Business.Common",
      "baseClass": null,
      "interfaces": [],
      "isAbstract": false,
      "isStatic": false,
      "methods": [],
      "properties": [],
      "storedProcedureCalls": [],
      "filePath": "MyEvaluations.Business.Common/DashBoard.cs"
    },
    {
      "name": "SingleEPA",
      "namespace": "MyEvaluations.Business.Common",
      "baseClass": null,
      "interfaces": [],
      "isAbstract": false,
      "isStatic": false,
      "methods": [],
      "properties": [],
      "storedProcedureCalls": [],
      "filePath": "MyEvaluations.Business.Common/DashBoard.cs"
    },
    {
      "name": "SingleEpaScoreOverTime",
      "namespace": "MyEvaluations.Business.Common",
      "baseClass": null,
      "interfaces": [],
      "isAbstract": false,
      "isStatic": false,
      "methods": [],
      "properties": [],
      "storedProcedureCalls": [],
      "filePath": "MyEvaluations.Business.Common/DashBoard.cs"
    },
    {
      "name": "PatientLogData",
      "namespace": "MyEvaluations.Business.Common",
      "baseClass": null,
      "interfaces": [],
      "isAbstract": false,
      "isStatic": false,
      "methods": [],
      "properties": [],
      "storedProcedureCalls": [],
      "filePath": "MyEvaluations.Business.Common/DashBoard.cs"
    },
    {
      "name": "PatientLogDataOutpatientHours",
      "namespace": "MyEvaluations.Business.Common",
      "baseClass": null,
      "interfaces": [],
      "isAbstract": false,
      "isStatic": false,
      "methods": [],
      "properties": [],
      "storedProcedureCalls": [],
      "filePath": "MyEvaluations.Business.Common/DashBoard.cs"
    },
    {
      "name": "PatientLogDataOutpatientHoursOverTime",
      "namespace": "MyEvaluations.Business.Common",
      "baseClass": null,
      "interfaces": [],
      "isAbstract": false,
      "isStatic": false,
      "methods": [],
      "properties": [],
      "storedProcedureCalls": [],
      "filePath": "MyEvaluations.Business.Common/DashBoard.cs"
    },
    {
      "name": "PatientLogDataSubmissionRate",
      "namespace": "MyEvaluations.Business.Common",
      "baseClass": null,
      "interfaces": [],
      "isAbstract": false,
      "isStatic": false,
      "methods": [],
      "properties": [],
      "storedProcedureCalls": [],
      "filePath": "MyEvaluations.Business.Common/DashBoard.cs"
    },
    {
      "name": "PatientLogDataSubmissionRateByPatientType",
      "namespace": "MyEvaluations.Business.Common",
      "baseClass": null,
      "interfaces": [],
      "isAbstract": false,
      "isStatic": false,
      "methods": [],
      "properties": [],
      "storedProcedureCalls": [],
      "filePath": "MyEvaluations.Business.Common/DashBoard.cs"
    },
    {
      "name": "PerLevelsubmissionRateByPatientType",
      "namespace": "MyEvaluations.Business.Common",
      "baseClass": null,
      "interfaces": [],
      "isAbstract": false,
      "isStatic": false,
      "methods": [],
      "properties": [],
      "storedProcedureCalls": [],
      "filePath": "MyEvaluations.Business.Common/DashBoard.cs"
    },
    {
      "name": "EmailValidation",
      "namespace": "MyEvaluations.Business.Common",
      "baseClass": null,
      "interfaces": [],
      "isAbstract": false,
      "isStatic": false,
      "methods": [],
      "properties": [],
      "storedProcedureCalls": [
        "CheckEmailStatus",
        "CheckEventEmailStatus"
      ],
      "filePath": "MyEvaluations.Business.Common/EmailValidation.cs"
    },
    {
      "name": "EventManager",
      "namespace": "MyEvaluations.Business.Common",
      "baseClass": "Manager",
      "interfaces": [],
      "isAbstract": false,
      "isStatic": false,
      "methods": [],
      "properties": [],
      "storedProcedureCalls": [
        "LogEvent",
        "LogEventDetail"
      ],
      "filePath": "MyEvaluations.Business.Common/EventManager.cs"
    },
    {
      "name": "FilePaths",
      "namespace": "MyEvaluations.Business.Common",
      "baseClass": null,
      "interfaces": [],
      "isAbstract": false,
      "isStatic": false,
      "methods": [],
      "properties": [],
      "storedProcedureCalls": [],
      "filePath": "MyEvaluations.Business.Common/FilePaths.cs"
    },
    {
      "name": "StringValue",
      "namespace": "MyEvaluations.Business.Common",
      "baseClass": "System.Attribute",
      "interfaces": [],
      "isAbstract": false,
      "isStatic": false,
      "methods": [],
      "properties": [],
      "storedProcedureCalls": [],
      "filePath": "MyEvaluations.Business.Common/FilePaths.cs"
    },
    {
      "name": "AuthenticationFailureAuditEvent",
      "namespace": "MyEvaluations.Business.Common",
      "baseClass": "System.Web.Management.WebAuthenticationFailureAuditEvent",
      "interfaces": [],
      "isAbstract": false,
      "isStatic": false,
      "methods": [],
      "properties": [],
      "storedProcedureCalls": [],
      "filePath": "MyEvaluations.Business.Common/LoggingManager.cs"
    },
    {
      "name": "ApplicationCustomErrorEvent",
      "namespace": "MyEvaluations.Business.Common",
      "baseClass": "System.Web.Management.WebErrorEvent",
      "interfaces": [],
      "isAbstract": false,
      "isStatic": false,
      "methods": [],
      "properties": [],
      "storedProcedureCalls": [],
      "filePath": "MyEvaluations.Business.Common/LoggingManager.cs"
    },
    {
      "name": "Manager",
      "namespace": "MyEvaluations.Business.Common",
      "baseClass": null,
      "interfaces": [],
      "isAbstract": true,
      "isStatic": false,
      "methods": [],
      "properties": [],
      "storedProcedureCalls": [],
      "filePath": "MyEvaluations.Business.Common/Manager.cs"
    },
    {
      "name": "ListItem",
      "namespace": "MyEvaluations.Business.Common",
      "baseClass": null,
      "interfaces": [],
      "isAbstract": false,
      "isStatic": false,
      "methods": [],
      "properties": [],
      "storedProcedureCalls": [],
      "filePath": "MyEvaluations.Business.Common/Manager.cs"
    },
    {
      "name": "UserFriendlyException",
      "namespace": "",
      "baseClass": "Exception",
      "interfaces": [],
      "isAbstract": false,
      "isStatic": false,
      "methods": [],
      "properties": [],
      "storedProcedureCalls": [],
      "filePath": "MyEvaluations.Business.Common/UserFriendlyException.cs"
    }
  ],
  "managerClasses": [
    "CacheManager",
    "EventManager",
    "Manager"
  ],
  "infoCounterparts": {
    "EventManager": "EventInfo"
  }
}