{
  "directory": "OnCall",
  "directoryPath": "Web/OnCall",
  "parsedAt": "2026-02-20T17:10:59.197Z",
  "fileCount": 4,
  "totalLines": 136,
  "files": [
    {
      "fileName": "Momentum.aspx.cs",
      "filePath": "Web/OnCall/Momentum.aspx.cs",
      "lineCount": 37,
      "className": "OnCall_Momentum",
      "namespace": "",
      "baseClass": "System.Web.UI.Page",
      "interfaces": [],
      "usingStatements": [
        "System.Collections.Generic",
        "System.Linq",
        "System.Web",
        "System.Web.UI",
        "System.Web.UI.WebControls",
        "MyEvaluations.Business.Security",
        "MyEvaluations.Business.DutyHours"
      ],
      "businessModuleRefs": [
        "Security",
        "DutyHours"
      ],
      "methods": [
        {
          "name": "UserBusiness",
          "returnType": " new",
          "visibility": "private",
          "parameters": [],
          "isStatic": false,
          "isAsync": false
        },
        {
          "name": "Page_Load",
          "returnType": "\n    protected void",
          "visibility": "private",
          "parameters": [
            "object sender",
            "EventArgs e"
          ],
          "isStatic": false,
          "isAsync": false
        }
      ],
      "storedProcedureCalls": [],
      "fileType": "code-behind"
    },
    {
      "fileName": "OnCall.aspx.cs",
      "filePath": "Web/OnCall/OnCall.aspx.cs",
      "lineCount": 38,
      "className": "OnCall_OnCall",
      "namespace": "",
      "baseClass": "BasePage",
      "interfaces": [],
      "usingStatements": [
        "System.Collections.Generic",
        "System.Web",
        "System.Web.UI",
        "System.Web.UI.WebControls",
        "MyEvaluations.Business.Security",
        "MyEvaluations.Business.DutyHours",
        "MyEvaluations.Business.TimeSheet"
      ],
      "businessModuleRefs": [
        "Security",
        "DutyHours",
        "TimeSheet"
      ],
      "methods": [
        {
          "name": "UserBusiness",
          "returnType": " new",
          "visibility": "private",
          "parameters": [],
          "isStatic": false,
          "isAsync": false
        },
        {
          "name": "Page_Load",
          "returnType": "\r\n\r\n    protected void",
          "visibility": "private",
          "parameters": [
            "object sender",
            "EventArgs e"
          ],
          "isStatic": false,
          "isAsync": false
        }
      ],
      "storedProcedureCalls": [],
      "fileType": "code-behind"
    },
    {
      "fileName": "QGenda.aspx.cs",
      "filePath": "Web/OnCall/QGenda.aspx.cs",
      "lineCount": 38,
      "className": "OnCall_QGenda",
      "namespace": "",
      "baseClass": "BasePage",
      "interfaces": [],
      "usingStatements": [
        "System.Collections.Generic",
        "System.Linq",
        "System.Web",
        "System.Web.UI",
        "System.Web.UI.WebControls",
        "MyEvaluations.Business.Security",
        "MyEvaluations.Business.DutyHours",
        "MyEvaluations.Business.TimeSheet"
      ],
      "businessModuleRefs": [
        "Security",
        "DutyHours",
        "TimeSheet"
      ],
      "methods": [
        {
          "name": "UserBusiness",
          "returnType": " new",
          "visibility": "private",
          "parameters": [],
          "isStatic": false,
          "isAsync": false
        },
        {
          "name": "Page_Load",
          "returnType": "\n\n    protected void",
          "visibility": "private",
          "parameters": [
            "object sender",
            "EventArgs e"
          ],
          "isStatic": false,
          "isAsync": false
        }
      ],
      "storedProcedureCalls": [],
      "fileType": "code-behind"
    },
    {
      "fileName": "Tangier.aspx.cs",
      "filePath": "Web/OnCall/Tangier.aspx.cs",
      "lineCount": 23,
      "className": "OnCall_Tangier",
      "namespace": "",
      "baseClass": "System.Web.UI.Page",
      "interfaces": [],
      "usingStatements": [
        "System.Collections.Generic",
        "System.Linq",
        "System.Web",
        "System.Web.UI",
        "System.Web.UI.WebControls",
        "MyEvaluations.Business.TimeSheet",
        "MyEvaluations.Business.Security"
      ],
      "businessModuleRefs": [
        "TimeSheet",
        "Security"
      ],
      "methods": [
        {
          "name": "Page_Load",
          "returnType": "\r\n    protected void",
          "visibility": "private",
          "parameters": [
            "object sender",
            "EventArgs e"
          ],
          "isStatic": false,
          "isAsync": false
        },
        {
          "name": "InitControls",
          "returnType": "\r",
          "visibility": "private",
          "parameters": [],
          "isStatic": false,
          "isAsync": false
        },
        {
          "name": "InitControls",
          "returnType": "\r\n\r\n    private void",
          "visibility": "private",
          "parameters": [],
          "isStatic": false,
          "isAsync": false
        }
      ],
      "storedProcedureCalls": [],
      "fileType": "code-behind"
    }
  ]
}